{
  "/MIDAS version" : "2.1",
  "/MIDAS git revision" : "Fri Oct 18 18:02:51 2024 -0700 - midas-2022-05-c-1467-geb625af1-dirty on branch develop",
  "/filename" : "roctower.json",
  "/ODB path" : "/Mu2e/RunConfigurations/roctower",

  "Name/key" : { "type" : 12, "item_size" : 32, "access_mode" : 7, "last_written" : 1731791002 },
  "Name" : "roctower",
  "RunType/key" : { "type" : 7, "access_mode" : 7, "last_written" : 1732890972 },
  "RunType" : 4,
  "UseRunInfoDB/key" : { "type" : 8, "access_mode" : 7, "last_written" : 1733095380 },
  "UseRunInfoDB" : true,
  "Calorimeter" : {
    "Initialized/key" : { "type" : 7, "access_mode" : 7, "last_written" : 0 },
    "Initialized" : 0,
    "Enabled/key" : { "type" : 7, "access_mode" : 7, "last_written" : 1731736087 },
    "Enabled" : 0,
    "Status/key" : { "type" : 7, "access_mode" : 7, "last_written" : 1731736095 },
    "Status" : 0,
    "Disk0" : {
      "Enabled/key" : { "type" : 7, "access_mode" : 7, "last_written" : 1733010889 },
      "Enabled" : 1,
      "Status/key" : { "type" : 7, "access_mode" : 7, "last_written" : 1733010569 },
      "Status" : 0
    },
    "Disk1" : {
      "Enabled/key" : { "type" : 7, "access_mode" : 7, "last_written" : 1733010574 },
      "Enabled" : 0,
      "Status/key" : { "type" : 7, "access_mode" : 7, "last_written" : 1733010574 },
      "Status" : 0
    },
    "MonitoringFrontend" : {
      "Name/key" : { "type" : 12, "item_size" : 32, "access_mode" : 7, "last_written" : 1733422709 },
      "Name" : "calmon",
      "Host/key" : { "type" : 12, "item_size" : 32, "access_mode" : 7, "last_written" : 1733422709 },
      "Host" : "mu2edaq22-ctrl",
      "# --------------------- 1/key" : { "type" : 12, "item_size" : 32, "access_mode" : 7, "last_written" : 1733422709 },
      "# --------------------- 1" : "---------- configurable element",
      "Enabled/key" : { "type" : 7, "access_mode" : 7, "last_written" : 1733422709 },
      "Enabled" : 0,
      "Status/key" : { "type" : 7, "access_mode" : 7, "last_written" : 1733422709 },
      "Status" : 0
    }
  },
  "CRV" : {
    "Initialized/key" : { "type" : 7, "access_mode" : 7, "last_written" : 0 },
    "Initialized" : 0,
    "Enabled/key" : { "type" : 7, "access_mode" : 7, "last_written" : 1731736018 },
    "Enabled" : 0,
    "Status/key" : { "type" : 7, "access_mode" : 7, "last_written" : 1731387720 },
    "Status" : -1,
    "CRV-U" : {
      "Enabled/key" : { "type" : 7, "access_mode" : 7, "last_written" : 1733017999 },
      "Enabled" : 0,
      "Status/key" : { "type" : 7, "access_mode" : 7, "last_written" : 1733018029 },
      "Status" : 0
    },
    "CRV-D" : {
      "Enabled/key" : { "type" : 7, "access_mode" : 7, "last_written" : 1733018017 },
      "Enabled" : 0,
      "Status/key" : { "type" : 7, "access_mode" : 7, "last_written" : 1733018041 },
      "Status" : -1
    },
    "CRV-L" : {
      "Enabled/key" : { "type" : 7, "access_mode" : 7, "last_written" : 1733018046 },
      "Enabled" : 0,
      "Status/key" : { "type" : 7, "access_mode" : 7, "last_written" : 1733018046 },
      "Status" : -1
    },
    "CRV-R" : {
      "Enabled/key" : { "type" : 7, "access_mode" : 7, "last_written" : 1733018055 },
      "Enabled" : 0,
      "Status/key" : { "type" : 7, "access_mode" : 7, "last_written" : 1733018055 },
      "Status" : -1
    },
    "CRV-Cryo-Out" : {
      "Enabled/key" : { "type" : 7, "access_mode" : 7, "last_written" : 1733018062 },
      "Enabled" : 0,
      "Status/key" : { "type" : 7, "access_mode" : 7, "last_written" : 1733018062 },
      "Status" : -1
    },
    "MonitoringFrontend" : {
      "Name/key" : { "type" : 12, "item_size" : 32, "access_mode" : 7, "last_written" : 1733422737 },
      "Name" : "crvmon",
      "Host/key" : { "type" : 12, "item_size" : 32, "access_mode" : 7, "last_written" : 1733422727 },
      "Host" : "mu2edaq22-ctrl",
      "# --------------------- 1/key" : { "type" : 12, "item_size" : 32, "access_mode" : 7, "last_written" : 1733422727 },
      "# --------------------- 1" : "---------- configurable element",
      "Enabled/key" : { "type" : 7, "access_mode" : 7, "last_written" : 1733422727 },
      "Enabled" : 0,
      "Status/key" : { "type" : 7, "access_mode" : 7, "last_written" : 1733422727 },
      "Status" : 0
    }
  },
  "DAQ" : {
    "CFO" : {
      "Enabled/key" : { "type" : 7, "access_mode" : 7, "last_written" : 1730837625 },
      "Enabled" : 1,
      "comment/key" : { "type" : 12, "item_size" : 32, "access_mode" : 7, "last_written" : 1730837625 },
      "comment" : "# emulated CFO",
      "EmulatedMode/key" : { "type" : 7, "access_mode" : 7, "last_written" : 1732916939 },
      "EmulatedMode" : 1,
      "External/key" : { "type" : 7, "access_mode" : 7, "last_written" : 1730837625 },
      "External" : 0,
      "Host/key" : { "type" : 12, "item_size" : 38, "access_mode" : 7, "last_written" : 1733076108 },
      "Host" : "mu2edaq22-ctrl.fnal.gov--is-it -used?",
      "EventMode/key" : { "type" : 7, "access_mode" : 7, "last_written" : 1733075979 },
      "EventMode" : 1,
      "NEventsPerTrain/key" : { "type" : 7, "access_mode" : 7, "last_written" : 1733001968 },
      "NEventsPerTrain" : 500,
      "EventWindowSize/key" : { "type" : 7, "access_mode" : 7, "last_written" : 1732982914 },
      "EventWindowSize" : 1000,
      "SleepTimeMs/key" : { "type" : 7, "access_mode" : 7, "last_written" : 1733001962 },
      "SleepTimeMs" : 500,
      "DTC/key" : { "type" : 16, "link": "/Mu2e/RunConfigurations/roctower/DAQ/mu2edaq22/DTC0", "access_mode" : 7, "last_written" : 1732916763 },
      "DTC" : "/Mu2e/RunConfigurations/roctower/DAQ/mu2edaq22/DTC0",
      "FirstEWTag/key" : { "type" : 18, "access_mode" : 7, "last_written" : 0 },
      "FirstEWTag" : "0x0000000000000000"
    },
    "TfmRpcHost/key" : { "type" : 12, "item_size" : 32, "access_mode" : 7, "last_written" : 1731087402 },
    "TfmRpcHost" : "mu2edaq22-ctrl",
    "Enabled/key" : { "type" : 7, "access_mode" : 7, "last_written" : 1731257019 },
    "Enabled" : 1,
    "Status/key" : { "type" : 7, "access_mode" : 7, "last_written" : 1731387861 },
    "Status" : 1,
    "mu2edaq04" : {
      "Enabled/key" : { "type" : 7, "access_mode" : 7, "last_written" : 1733014405 },
      "Enabled" : 0,
      "Status/key" : { "type" : 7, "access_mode" : 7, "last_written" : 1733014406 },
      "Status" : 0
    },
    "mu2edaq09" : {
      "Enabled/key" : { "type" : 7, "access_mode" : 7, "last_written" : 1733014417 },
      "Enabled" : 0,
      "Status/key" : { "type" : 7, "access_mode" : 7, "last_written" : 1733014417 },
      "Status" : 0
    },
    "mu2edaq10" : {
      "Enabled/key" : { "type" : 7, "access_mode" : 7, "last_written" : 1733014417 },
      "Enabled" : 0,
      "Status/key" : { "type" : 7, "access_mode" : 7, "last_written" : 1733014417 },
      "Status" : 0
    },
    "mu2edaq11" : {
      "Enabled/key" : { "type" : 7, "access_mode" : 7, "last_written" : 1733014418 },
      "Enabled" : 0,
      "Status/key" : { "type" : 7, "access_mode" : 7, "last_written" : 1733014418 },
      "Status" : 0
    },
    "mu2edaq13" : {
      "Enabled/key" : { "type" : 7, "access_mode" : 7, "last_written" : 1733014418 },
      "Enabled" : 0,
      "Status/key" : { "type" : 7, "access_mode" : 7, "last_written" : 1733014418 },
      "Status" : 0
    },
    "mu2edaq14" : {
      "Enabled/key" : { "type" : 7, "access_mode" : 7, "last_written" : 1733014419 },
      "Enabled" : 0,
      "Status/key" : { "type" : 7, "access_mode" : 7, "last_written" : 1733021942 },
      "Status" : -1
    },
    "mu2edaq22" : {
      "DTC0" : {
        "PcieAddress/key" : { "type" : 7, "access_mode" : 7, "last_written" : 1732916852 },
        "PcieAddress" : 0,
        "EmulatesCFO/key" : { "type" : 7, "access_mode" : 7, "last_written" : 1733074004 },
        "EmulatesCFO" : 1,
        "LinkMask/key" : { "type" : 7, "access_mode" : 7, "last_written" : 1733079305 },
        "LinkMask" : 273,
        "ReadoutMode/key" : { "type" : 7, "access_mode" : 7, "last_written" : 1733094152 },
        "ReadoutMode" : 1,
        "JAMode/key" : { "type" : 7, "access_mode" : 7, "last_written" : 1733092215 },
        "JAMode" : 1,
        "SampleEdgeMode/key" : { "type" : 7, "access_mode" : 7, "last_written" : 1733074369 },
        "SampleEdgeMode" : 0,
        "AutogenDRP/key" : { "type" : 7, "access_mode" : 7, "last_written" : 1730837625 },
        "AutogenDRP" : 1,
        "EnableClockMarkers/key" : { "type" : 7, "access_mode" : 7, "last_written" : 1730837625 },
        "EnableClockMarkers" : 0,
        "EnableCFOLinkRX/key" : { "type" : 7, "access_mode" : 7, "last_written" : 1733091932 },
        "EnableCFOLinkRX" : 0,
        "DtcID/key" : { "type" : 7, "access_mode" : 7, "last_written" : 0 },
        "DtcID" : 0,
        "PartitionID/key" : { "type" : 7, "access_mode" : 7, "last_written" : 1733079930 },
        "PartitionID" : 11,
        "MacAddrByte/key" : { "type" : 7, "access_mode" : 7, "last_written" : 0 },
        "MacAddrByte" : 0,
        "OnSpill/key" : { "type" : 7, "access_mode" : 7, "last_written" : 1733091835 },
        "OnSpill" : 1,
        "ROC0/key" : { "type" : 16, "link": "/Mu2e/RunConfigurations/roctower/Tracker/Station_00/Plane_00/Panel_00", "access_mode" : 7, "last_written" : 1731370879 },
        "ROC0" : "/Mu2e/RunConfigurations/roctower/Tracker/Station_00/Plane_00/Panel_00",
        "ROC1/key" : { "type" : 16, "link": "/Mu2e/RunConfigurations/roctower/Tracker/Station_00/Plane_00/Panel_01", "access_mode" : 7, "last_written" : 1731370961 },
        "ROC1" : "/Mu2e/RunConfigurations/roctower/Tracker/Station_00/Plane_00/Panel_01",
        "ROC2/key" : { "type" : 16, "link": "/Mu2e/RunConfigurations/roctower/Tracker/Station_00/Plane_00/Panel_02", "access_mode" : 7, "last_written" : 1731371076 },
        "ROC2" : "/Mu2e/RunConfigurations/roctower/Tracker/Station_00/Plane_00/Panel_02",
        "ROC3/key" : { "type" : 16, "link": "/Mu2e/RunConfigurations/roctower/Tracker/Station_00/Plane_00/Panel_03", "access_mode" : 7, "last_written" : 1731371356 },
        "ROC3" : "/Mu2e/RunConfigurations/roctower/Tracker/Station_00/Plane_00/Panel_03",
        "ROC4/key" : { "type" : 16, "link": "/Mu2e/RunConfigurations/roctower/Tracker/Station_00/Plane_00/Panel_04", "access_mode" : 7, "last_written" : 1731371139 },
        "ROC4" : "/Mu2e/RunConfigurations/roctower/Tracker/Station_00/Plane_00/Panel_04",
        "ROC5/key" : { "type" : 16, "link": "/Mu2e/RunConfigurations/roctower/Tracker/Station_00/Plane_00/Panel_05", "access_mode" : 7, "last_written" : 1731371363 },
        "ROC5" : "/Mu2e/RunConfigurations/roctower/Tracker/Station_00/Plane_00/Panel_05",
        "# comment_#_2 -------------/key" : { "type" : 12, "item_size" : 54, "access_mode" : 7, "last_written" : 1733079052 },
        "# comment_#_2 -------------" : "------------ tracker-specific ",
        "Station/key" : { "type" : 7, "access_mode" : 7, "last_written" : 0 },
        "Station" : 0,
        "Plane/key" : { "type" : 7, "access_mode" : 7, "last_written" : 0 },
        "Plane" : 0,
        "# comment_#_3 -------------/key" : { "type" : 12, "item_size" : 55, "access_mode" : 7, "last_written" : 1733079036 },
        "# comment_#_3 -------------" : "--------- configurable element ",
        "Enabled/key" : { "type" : 7, "access_mode" : 7, "last_written" : 1730837625 },
        "Enabled" : 1,
        "Status/key" : { "type" : 7, "access_mode" : 7, "last_written" : 1731377902 },
        "Status" : 0
      },
      "DTC1" : {
        "PCIEAddress/key" : { "type" : 7, "access_mode" : 7, "last_written" : 1730837625 },
        "PCIEAddress" : 1,
        "EmulatesCFO/key" : { "type" : 7, "access_mode" : 7, "last_written" : 0 },
        "EmulatesCFO" : 0,
        "LinkMask/key" : { "type" : 7, "access_mode" : 7, "last_written" : 1733079319 },
        "LinkMask" : 65809,
        "AutogenDRP/key" : { "type" : 7, "access_mode" : 7, "last_written" : 1730837625 },
        "AutogenDRP" : 1,
        "# --- comment_#0/key" : { "type" : 12, "item_size" : 47, "access_mode" : 7, "last_written" : 1733094189 },
        "# --- comment_#0" : "--------- ROC readout mode: 0:patterns 1:digis",
        "ReadoutMode/key" : { "type" : 7, "access_mode" : 7, "last_written" : 1733094219 },
        "ReadoutMode" : 1,
        "JAMode/key" : { "type" : 7, "access_mode" : 7, "last_written" : 1733092253 },
        "JAMode" : 1,
        "SampleEdgeMode/key" : { "type" : 7, "access_mode" : 7, "last_written" : 1730837625 },
        "SampleEdgeMode" : 0,
        "EnableClockMarkers/key" : { "type" : 7, "access_mode" : 7, "last_written" : 1730837625 },
        "EnableClockMarkers" : 0,
        "EnableCFOLinkRX/key" : { "type" : 7, "access_mode" : 7, "last_written" : 1730837625 },
        "EnableCFOLinkRX" : 1,
        "DtcID/key" : { "type" : 7, "access_mode" : 7, "last_written" : 1731087292 },
        "DtcID" : 1,
        "PartitionID/key" : { "type" : 7, "access_mode" : 7, "last_written" : 1733079946 },
        "PartitionID" : 11,
        "MacAddrByte/key" : { "type" : 7, "access_mode" : 7, "last_written" : 1731087287 },
        "MacAddrByte" : 0,
        "OnSpill/key" : { "type" : 7, "access_mode" : 7, "last_written" : 1733091863 },
        "OnSpill" : 1,
        "# comment_#_3 -------------/key" : { "type" : 12, "item_size" : 55, "access_mode" : 7, "last_written" : 1733078957 },
        "# comment_#_3 -------------" : "-------------------------------- configurable element ",
        "ReadoutMode/key" : { "type" : 7, "access_mode" : 7, "last_written" : 1731087287 },
        "ReadoutMode" : 0,
        "Enabled/key" : { "type" : 7, "access_mode" : 7, "last_written" : 1732568821 },
        "Enabled" : 1,
        "Status/key" : { "type" : 7, "access_mode" : 7, "last_written" : 1732917073 },
        "Status" : 0
      },
      "Artdaq" : {
        "br01" : {
          "Active/key" : { "type" : 7, "access_mode" : 7, "last_written" : 1730837625 },
          "Active" : 1,
          "Rank/key" : { "type" : 7, "access_mode" : 7, "last_written" : 1730837625 },
          "Rank" : 0,
          "XmlrpcPort/key" : { "type" : 7, "access_mode" : 7, "last_written" : 1730837625 },
          "XmlrpcPort" : 21101,
          "DTC/key" : { "type" : 16, "link": "/Mu2e/RunConfigurations/roctower/DAQ/mu2edaq22/DTC0", "access_mode" : 7, "last_written" : 1730837743 },
          "DTC" : "/Mu2e/RunConfigurations/roctower/DAQ/mu2edaq22/DTC0",
          "Status/key" : { "type" : 7, "access_mode" : 7, "last_written" : 0 },
          "Status" : 0
        },
        "br02" : {
          "Active/key" : { "type" : 7, "access_mode" : 7, "last_written" : 1732568843 },
          "Active" : 1,
          "Rank/key" : { "type" : 7, "access_mode" : 7, "last_written" : 1730837625 },
          "Rank" : 1,
          "XmlrpcPort/key" : { "type" : 7, "access_mode" : 7, "last_written" : 1730837625 },
          "XmlrpcPort" : 21102,
          "DTC/key" : { "type" : 16, "link": "/Mu2e/RunConfigurations/roctower/DAQ/mu2edaq22/DTC1", "access_mode" : 7, "last_written" : 1730837752 },
          "DTC" : "/Mu2e/RunConfigurations/roctower/DAQ/mu2edaq22/DTC1",
          "Status/key" : { "type" : 7, "access_mode" : 7, "last_written" : 0 },
          "Status" : 0
        },
        "eb01" : {
          "Active/key" : { "type" : 7, "access_mode" : 7, "last_written" : 1730837625 },
          "Active" : 1,
          "Rank/key" : { "type" : 7, "access_mode" : 7, "last_written" : 1730837625 },
          "Rank" : 2,
          "XmlrpcPort/key" : { "type" : 7, "access_mode" : 7, "last_written" : 1730837625 },
          "XmlrpcPort" : 21201,
          "Status/key" : { "type" : 7, "access_mode" : 7, "last_written" : 0 },
          "Status" : 0
        },
        "dl01" : {
          "Active/key" : { "type" : 7, "access_mode" : 7, "last_written" : 1730855265 },
          "Active" : 1,
          "Rank/key" : { "type" : 7, "access_mode" : 7, "last_written" : 1730837625 },
          "Rank" : 3,
          "XmlrpcPort/key" : { "type" : 7, "access_mode" : 7, "last_written" : 1730837625 },
          "XmlrpcPort" : 21301,
          "Status/key" : { "type" : 7, "access_mode" : 7, "last_written" : 0 },
          "Status" : 0
        },
        "ds01" : {
          "Active/key" : { "type" : 7, "access_mode" : 7, "last_written" : 1730837625 },
          "Active" : 1,
          "Rank/key" : { "type" : 7, "access_mode" : 7, "last_written" : 1730837625 },
          "Rank" : 4,
          "XmlrpcPort/key" : { "type" : 7, "access_mode" : 7, "last_written" : 1730837625 },
          "XmlrpcPort" : 10500,
          "Status/key" : { "type" : 7, "access_mode" : 7, "last_written" : 0 },
          "Status" : 0
        }
      },
      "Status/key" : { "type" : 7, "access_mode" : 7, "last_written" : 1731377527 },
      "Status" : 0,
      "Enabled/key" : { "type" : 7, "access_mode" : 7, "last_written" : 1733014328 },
      "Enabled" : 1
    },
    "MonitoringFrontend" : {
      "Name/key" : { "type" : 12, "item_size" : 32, "access_mode" : 7, "last_written" : 1733422758 },
      "Name" : "daqmon",
      "Host/key" : { "type" : 12, "item_size" : 32, "access_mode" : 7, "last_written" : 1733422749 },
      "Host" : "mu2edaq22-ctrl",
      "# --------------------- 1/key" : { "type" : 12, "item_size" : 32, "access_mode" : 7, "last_written" : 1733422749 },
      "# --------------------- 1" : "---------- configurable element",
      "Enabled/key" : { "type" : 7, "access_mode" : 7, "last_written" : 1733422749 },
      "Enabled" : 0,
      "Status/key" : { "type" : 7, "access_mode" : 7, "last_written" : 1733422749 },
      "Status" : 0
    }
  },
  "EXM" : {
    "Initialized/key" : { "type" : 7, "access_mode" : 7, "last_written" : 0 },
    "Initialized" : 0,
    "Enabled/key" : { "type" : 7, "access_mode" : 7, "last_written" : 1731214813 },
    "Enabled" : 0,
    "Status/key" : { "type" : 7, "access_mode" : 7, "last_written" : 0 },
    "Status" : 0,
    "Element0" : {
      "Enabled/key" : { "type" : 7, "access_mode" : 7, "last_written" : 1733012174 },
      "Enabled" : 0,
      "Status/key" : { "type" : 7, "access_mode" : 7, "last_written" : 1733012174 },
      "Status" : 0
    },
    "MonitoringFrontend" : {
      "Name/key" : { "type" : 12, "item_size" : 32, "access_mode" : 7, "last_written" : 1733422779 },
      "Name" : "exmmon",
      "Host/key" : { "type" : 12, "item_size" : 32, "access_mode" : 7, "last_written" : 1733422770 },
      "Host" : "mu2edaq22-ctrl",
      "# --------------------- 1/key" : { "type" : 12, "item_size" : 32, "access_mode" : 7, "last_written" : 1733422770 },
      "# --------------------- 1" : "---------- configurable element",
      "Enabled/key" : { "type" : 7, "access_mode" : 7, "last_written" : 1733422770 },
      "Enabled" : 0,
      "Status/key" : { "type" : 7, "access_mode" : 7, "last_written" : 1733422770 },
      "Status" : 0
    }
  },
  "STM" : {
    "Initialized/key" : { "type" : 7, "access_mode" : 7, "last_written" : 0 },
    "Initialized" : 0,
    "Enabled/key" : { "type" : 7, "access_mode" : 7, "last_written" : 1731736070 },
    "Enabled" : 0,
    "Status/key" : { "type" : 7, "access_mode" : 7, "last_written" : 0 },
    "Status" : 0,
    "Element0" : {
      "Enabled/key" : { "type" : 7, "access_mode" : 7, "last_written" : 1733011924 },
      "Enabled" : 0,
      "Status/key" : { "type" : 7, "access_mode" : 7, "last_written" : 1733011924 },
      "Status" : 0
    },
    "MonitoringFrontend" : {
      "Name/key" : { "type" : 12, "item_size" : 32, "access_mode" : 7, "last_written" : 1733422795 },
      "Name" : "stmmon",
      "Host/key" : { "type" : 12, "item_size" : 32, "access_mode" : 7, "last_written" : 1733422787 },
      "Host" : "mu2edaq22-ctrl",
      "# --------------------- 1/key" : { "type" : 12, "item_size" : 32, "access_mode" : 7, "last_written" : 1733422787 },
      "# --------------------- 1" : "---------- configurable element",
      "Enabled/key" : { "type" : 7, "access_mode" : 7, "last_written" : 1733422787 },
      "Enabled" : 0,
      "Status/key" : { "type" : 7, "access_mode" : 7, "last_written" : 1733422787 },
      "Status" : 0
    }
  },
  "Tracker" : {
    "Station_00" : {
      "Plane_00" : {
        "Panel_00" : {
          "Name/key" : { "type" : 12, "item_size" : 32, "access_mode" : 7, "last_written" : 1731256441 },
          "Name" : "MN900",
          "ID/key" : { "type" : 12, "item_size" : 32, "access_mode" : 7, "last_written" : 1730837589 },
          "ID" : "",
          "FirstChannel/key" : { "type" : 7, "access_mode" : 7, "last_written" : 1730837589 },
          "FirstChannel" : 0,
          "Threshold_CAL/key" : { "type" : 7, "num_values" : 96, "access_mode" : 7, "last_written" : 1730837589 },
          "Threshold_CAL" : [ 0, 0, 0, 0, 0, 0, 0, 0, 0, 0, 0, 0, 0, 0, 0, 0, 0, 0, 0, 0, 0, 0, 0, 0, 0, 0, 0, 0, 0, 0, 0, 0, 0, 0, 0, 0, 0, 0, 0, 0, 0, 0, 0, 0, 0, 0, 0, 0, 0, 0, 0, 0, 0, 0, 0, 0, 0, 0, 0, 0, 0, 0, 0, 0, 0, 0, 0, 0, 0, 0, 0, 0, 0, 0, 0, 0, 0, 0, 0, 0, 0, 0, 0, 0, 0, 0, 0, 0, 0, 0, 0, 0, 0, 0, 0, 0 ],
          "Threshold_HV/key" : { "type" : 7, "num_values" : 96, "access_mode" : 7, "last_written" : 1730837589 },
          "Threshold_HV" : [ 0, 0, 0, 0, 0, 0, 0, 0, 0, 0, 0, 0, 0, 0, 0, 0, 0, 0, 0, 0, 0, 0, 0, 0, 0, 0, 0, 0, 0, 0, 0, 0, 0, 0, 0, 0, 0, 0, 0, 0, 0, 0, 0, 0, 0, 0, 0, 0, 0, 0, 0, 0, 0, 0, 0, 0, 0, 0, 0, 0, 0, 0, 0, 0, 0, 0, 0, 0, 0, 0, 0, 0, 0, 0, 0, 0, 0, 0, 0, 0, 0, 0, 0, 0, 0, 0, 0, 0, 0, 0, 0, 0, 0, 0, 0, 0 ],
          "Gain_CAL/key" : { "type" : 7, "num_values" : 96, "access_mode" : 7, "last_written" : 1730837589 },
          "Gain_CAL" : [ 0, 0, 0, 0, 0, 0, 0, 0, 0, 0, 0, 0, 0, 0, 0, 0, 0, 0, 0, 0, 0, 0, 0, 0, 0, 0, 0, 0, 0, 0, 0, 0, 0, 0, 0, 0, 0, 0, 0, 0, 0, 0, 0, 0, 0, 0, 0, 0, 0, 0, 0, 0, 0, 0, 0, 0, 0, 0, 0, 0, 0, 0, 0, 0, 0, 0, 0, 0, 0, 0, 0, 0, 0, 0, 0, 0, 0, 0, 0, 0, 0, 0, 0, 0, 0, 0, 0, 0, 0, 0, 0, 0, 0, 0, 0, 0 ],
          "Gain_HV/key" : { "type" : 7, "num_values" : 96, "access_mode" : 7, "last_written" : 1730837589 },
          "Gain_HV" : [ 0, 0, 0, 0, 0, 0, 0, 0, 0, 0, 0, 0, 0, 0, 0, 0, 0, 0, 0, 0, 0, 0, 0, 0, 0, 0, 0, 0, 0, 0, 0, 0, 0, 0, 0, 0, 0, 0, 0, 0, 0, 0, 0, 0, 0, 0, 0, 0, 0, 0, 0, 0, 0, 0, 0, 0, 0, 0, 0, 0, 0, 0, 0, 0, 0, 0, 0, 0, 0, 0, 0, 0, 0, 0, 0, 0, 0, 0, 0, 0, 0, 0, 0, 0, 0, 0, 0, 0, 0, 0, 0, 0, 0, 0, 0, 0 ],
          "ChannelMask/key" : { "type" : 6, "num_values" : 3, "access_mode" : 7, "last_written" : 1731111322 },
          "ChannelMask" : [ "0xffffffff", "0xffffffff", "0xffffffff" ],
          "# comment : Status:/key" : { "type" : 12, "item_size" : 59, "access_mode" : 7, "last_written" : 1731256354 },
          "# comment : Status:" : "0: undefined 1:being configured 2: configured -1: in error",
          "Enabled/key" : { "type" : 7, "access_mode" : 7, "last_written" : 1731256824 },
          "Enabled" : 1,
          "Status/key" : { "type" : 7, "access_mode" : 7, "last_written" : 0 },
          "Status" : 0
        },
        "Panel_01" : {
          "Name/key" : { "type" : 12, "item_size" : 32, "access_mode" : 7, "last_written" : 1731256472 },
          "Name" : "MN901",
          "Enabled/key" : { "type" : 7, "access_mode" : 7, "last_written" : 1731256890 },
          "Enabled" : 1,
          "# comment : Status:/key" : { "type" : 12, "item_size" : 59, "access_mode" : 7, "last_written" : 1731256387 },
          "# comment : Status:" : "0: undefined 1:being configured 2: configured -1: in error",
          "Status/key" : { "type" : 7, "access_mode" : 7, "last_written" : 1731256387 },
          "Status" : 0,
          "Threshold_CAL/key" : { "type" : 7, "num_values" : 96, "access_mode" : 7, "last_written" : 1731791211 },
          "Threshold_CAL" : [ 0, 0, 0, 0, 0, 0, 0, 0, 0, 0, 0, 0, 0, 0, 0, 0, 0, 0, 0, 0, 0, 0, 0, 0, 0, 0, 0, 0, 0, 0, 0, 0, 0, 0, 0, 0, 0, 0, 0, 0, 0, 0, 0, 0, 0, 0, 0, 0, 0, 0, 0, 0, 0, 0, 0, 0, 0, 0, 0, 0, 0, 0, 0, 0, 0, 0, 0, 0, 0, 0, 0, 0, 0, 0, 0, 0, 0, 0, 0, 0, 0, 0, 0, 0, 0, 0, 0, 0, 0, 0, 0, 0, 0, 0, 0, 0 ],
          "Threshold_HV/key" : { "type" : 7, "num_values" : 96, "access_mode" : 7, "last_written" : 1731791211 },
          "Threshold_HV" : [ 0, 0, 0, 0, 0, 0, 0, 0, 0, 0, 0, 0, 0, 0, 0, 0, 0, 0, 0, 0, 0, 0, 0, 0, 0, 0, 0, 0, 0, 0, 0, 0, 0, 0, 0, 0, 0, 0, 0, 0, 0, 0, 0, 0, 0, 0, 0, 0, 0, 0, 0, 0, 0, 0, 0, 0, 0, 0, 0, 0, 0, 0, 0, 0, 0, 0, 0, 0, 0, 0, 0, 0, 0, 0, 0, 0, 0, 0, 0, 0, 0, 0, 0, 0, 0, 0, 0, 0, 0, 0, 0, 0, 0, 0, 0, 0 ],
          "Gain_CAL/key" : { "type" : 7, "num_values" : 96, "access_mode" : 7, "last_written" : 1731791236 },
          "Gain_CAL" : [ 0, 0, 0, 0, 0, 0, 0, 0, 0, 0, 0, 0, 0, 0, 0, 0, 0, 0, 0, 0, 0, 0, 0, 0, 0, 0, 0, 0, 0, 0, 0, 0, 0, 0, 0, 0, 0, 0, 0, 0, 0, 0, 0, 0, 0, 0, 0, 0, 0, 0, 0, 0, 0, 0, 0, 0, 0, 0, 0, 0, 0, 0, 0, 0, 0, 0, 0, 0, 0, 0, 0, 0, 0, 0, 0, 0, 0, 0, 0, 0, 0, 0, 0, 0, 0, 0, 0, 0, 0, 0, 0, 0, 0, 0, 0, 0 ],
          "Gain_HV/key" : { "type" : 7, "num_values" : 96, "access_mode" : 7, "last_written" : 1731791236 },
          "Gain_HV" : [ 0, 0, 0, 0, 0, 0, 0, 0, 0, 0, 0, 0, 0, 0, 0, 0, 0, 0, 0, 0, 0, 0, 0, 0, 0, 0, 0, 0, 0, 0, 0, 0, 0, 0, 0, 0, 0, 0, 0, 0, 0, 0, 0, 0, 0, 0, 0, 0, 0, 0, 0, 0, 0, 0, 0, 0, 0, 0, 0, 0, 0, 0, 0, 0, 0, 0, 0, 0, 0, 0, 0, 0, 0, 0, 0, 0, 0, 0, 0, 0, 0, 0, 0, 0, 0, 0, 0, 0, 0, 0, 0, 0, 0, 0, 0, 0 ],
          "ChannelMask/key" : { "type" : 6, "num_values" : 3, "access_mode" : 7, "last_written" : 1731791236 },
          "ChannelMask" : [ "0xffffffff", "0xffffffff", "0xffffffff" ]
        },
        "Panel_02" : {
          "Name/key" : { "type" : 12, "item_size" : 32, "access_mode" : 7, "last_written" : 1731256490 },
          "Name" : "MN902",
          "Enabled/key" : { "type" : 7, "access_mode" : 7, "last_written" : 1731256899 },
          "Enabled" : 1,
          "# comment : Status:/key" : { "type" : 12, "item_size" : 59, "access_mode" : 7, "last_written" : 1731256395 },
          "# comment : Status:" : "0: undefined 1:being configured 2: configured -1: in error",
          "Status/key" : { "type" : 7, "access_mode" : 7, "last_written" : 1731256395 },
          "Status" : 0,
          "Threshold_CAL/key" : { "type" : 7, "num_values" : 96, "access_mode" : 7, "last_written" : 1731791260 },
          "Threshold_CAL" : [ 0, 0, 0, 0, 0, 0, 0, 0, 0, 0, 0, 0, 0, 0, 0, 0, 0, 0, 0, 0, 0, 0, 0, 0, 0, 0, 0, 0, 0, 0, 0, 0, 0, 0, 0, 0, 0, 0, 0, 0, 0, 0, 0, 0, 0, 0, 0, 0, 0, 0, 0, 0, 0, 0, 0, 0, 0, 0, 0, 0, 0, 0, 0, 0, 0, 0, 0, 0, 0, 0, 0, 0, 0, 0, 0, 0, 0, 0, 0, 0, 0, 0, 0, 0, 0, 0, 0, 0, 0, 0, 0, 0, 0, 0, 0, 0 ],
          "Threshold_HV/key" : { "type" : 7, "num_values" : 96, "access_mode" : 7, "last_written" : 1731791260 },
          "Threshold_HV" : [ 0, 0, 0, 0, 0, 0, 0, 0, 0, 0, 0, 0, 0, 0, 0, 0, 0, 0, 0, 0, 0, 0, 0, 0, 0, 0, 0, 0, 0, 0, 0, 0, 0, 0, 0, 0, 0, 0, 0, 0, 0, 0, 0, 0, 0, 0, 0, 0, 0, 0, 0, 0, 0, 0, 0, 0, 0, 0, 0, 0, 0, 0, 0, 0, 0, 0, 0, 0, 0, 0, 0, 0, 0, 0, 0, 0, 0, 0, 0, 0, 0, 0, 0, 0, 0, 0, 0, 0, 0, 0, 0, 0, 0, 0, 0, 0 ],
          "Gain_CAL/key" : { "type" : 7, "num_values" : 96, "access_mode" : 7, "last_written" : 1731791260 },
          "Gain_CAL" : [ 0, 0, 0, 0, 0, 0, 0, 0, 0, 0, 0, 0, 0, 0, 0, 0, 0, 0, 0, 0, 0, 0, 0, 0, 0, 0, 0, 0, 0, 0, 0, 0, 0, 0, 0, 0, 0, 0, 0, 0, 0, 0, 0, 0, 0, 0, 0, 0, 0, 0, 0, 0, 0, 0, 0, 0, 0, 0, 0, 0, 0, 0, 0, 0, 0, 0, 0, 0, 0, 0, 0, 0, 0, 0, 0, 0, 0, 0, 0, 0, 0, 0, 0, 0, 0, 0, 0, 0, 0, 0, 0, 0, 0, 0, 0, 0 ],
          "Gain_HV/key" : { "type" : 7, "num_values" : 96, "access_mode" : 7, "last_written" : 1731791260 },
          "Gain_HV" : [ 0, 0, 0, 0, 0, 0, 0, 0, 0, 0, 0, 0, 0, 0, 0, 0, 0, 0, 0, 0, 0, 0, 0, 0, 0, 0, 0, 0, 0, 0, 0, 0, 0, 0, 0, 0, 0, 0, 0, 0, 0, 0, 0, 0, 0, 0, 0, 0, 0, 0, 0, 0, 0, 0, 0, 0, 0, 0, 0, 0, 0, 0, 0, 0, 0, 0, 0, 0, 0, 0, 0, 0, 0, 0, 0, 0, 0, 0, 0, 0, 0, 0, 0, 0, 0, 0, 0, 0, 0, 0, 0, 0, 0, 0, 0, 0 ],
          "ChannelMask/key" : { "type" : 6, "num_values" : 3, "access_mode" : 7, "last_written" : 1731791260 },
          "ChannelMask" : [ "0xffffffff", "0xffffffff", "0xffffffff" ]
        },
        "Panel_03" : {
          "Name/key" : { "type" : 12, "item_size" : 32, "access_mode" : 7, "last_written" : 1731256509 },
          "Name" : "MN903",
          "Enabled/key" : { "type" : 7, "access_mode" : 7, "last_written" : 1731256904 },
          "Enabled" : 1,
          "Status/key" : { "type" : 7, "access_mode" : 7, "last_written" : 1731256401 },
          "Status" : 0,
          "Threshold_CAL/key" : { "type" : 7, "num_values" : 96, "access_mode" : 7, "last_written" : 1731791269 },
          "Threshold_CAL" : [ 0, 0, 0, 0, 0, 0, 0, 0, 0, 0, 0, 0, 0, 0, 0, 0, 0, 0, 0, 0, 0, 0, 0, 0, 0, 0, 0, 0, 0, 0, 0, 0, 0, 0, 0, 0, 0, 0, 0, 0, 0, 0, 0, 0, 0, 0, 0, 0, 0, 0, 0, 0, 0, 0, 0, 0, 0, 0, 0, 0, 0, 0, 0, 0, 0, 0, 0, 0, 0, 0, 0, 0, 0, 0, 0, 0, 0, 0, 0, 0, 0, 0, 0, 0, 0, 0, 0, 0, 0, 0, 0, 0, 0, 0, 0, 0 ],
          "Threshold_HV/key" : { "type" : 7, "num_values" : 96, "access_mode" : 7, "last_written" : 1731791269 },
          "Threshold_HV" : [ 0, 0, 0, 0, 0, 0, 0, 0, 0, 0, 0, 0, 0, 0, 0, 0, 0, 0, 0, 0, 0, 0, 0, 0, 0, 0, 0, 0, 0, 0, 0, 0, 0, 0, 0, 0, 0, 0, 0, 0, 0, 0, 0, 0, 0, 0, 0, 0, 0, 0, 0, 0, 0, 0, 0, 0, 0, 0, 0, 0, 0, 0, 0, 0, 0, 0, 0, 0, 0, 0, 0, 0, 0, 0, 0, 0, 0, 0, 0, 0, 0, 0, 0, 0, 0, 0, 0, 0, 0, 0, 0, 0, 0, 0, 0, 0 ],
          "Gain_CAL/key" : { "type" : 7, "num_values" : 96, "access_mode" : 7, "last_written" : 1731791269 },
          "Gain_CAL" : [ 0, 0, 0, 0, 0, 0, 0, 0, 0, 0, 0, 0, 0, 0, 0, 0, 0, 0, 0, 0, 0, 0, 0, 0, 0, 0, 0, 0, 0, 0, 0, 0, 0, 0, 0, 0, 0, 0, 0, 0, 0, 0, 0, 0, 0, 0, 0, 0, 0, 0, 0, 0, 0, 0, 0, 0, 0, 0, 0, 0, 0, 0, 0, 0, 0, 0, 0, 0, 0, 0, 0, 0, 0, 0, 0, 0, 0, 0, 0, 0, 0, 0, 0, 0, 0, 0, 0, 0, 0, 0, 0, 0, 0, 0, 0, 0 ],
          "Gain_HV/key" : { "type" : 7, "num_values" : 96, "access_mode" : 7, "last_written" : 1731791269 },
          "Gain_HV" : [ 0, 0, 0, 0, 0, 0, 0, 0, 0, 0, 0, 0, 0, 0, 0, 0, 0, 0, 0, 0, 0, 0, 0, 0, 0, 0, 0, 0, 0, 0, 0, 0, 0, 0, 0, 0, 0, 0, 0, 0, 0, 0, 0, 0, 0, 0, 0, 0, 0, 0, 0, 0, 0, 0, 0, 0, 0, 0, 0, 0, 0, 0, 0, 0, 0, 0, 0, 0, 0, 0, 0, 0, 0, 0, 0, 0, 0, 0, 0, 0, 0, 0, 0, 0, 0, 0, 0, 0, 0, 0, 0, 0, 0, 0, 0, 0 ],
          "ChannelMask/key" : { "type" : 6, "num_values" : 3, "access_mode" : 7, "last_written" : 1731791269 },
          "ChannelMask" : [ "0xffffffff", "0xffffffff", "0xffffffff" ]
        },
        "Panel_04" : {
          "Name/key" : { "type" : 12, "item_size" : 32, "access_mode" : 7, "last_written" : 1731256523 },
          "Name" : "MN904",
          "Threshold_CAL/key" : { "type" : 7, "num_values" : 96, "access_mode" : 7, "last_written" : 1731791277 },
          "Threshold_CAL" : [ 0, 0, 0, 0, 0, 0, 0, 0, 0, 0, 0, 0, 0, 0, 0, 0, 0, 0, 0, 0, 0, 0, 0, 0, 0, 0, 0, 0, 0, 0, 0, 0, 0, 0, 0, 0, 0, 0, 0, 0, 0, 0, 0, 0, 0, 0, 0, 0, 0, 0, 0, 0, 0, 0, 0, 0, 0, 0, 0, 0, 0, 0, 0, 0, 0, 0, 0, 0, 0, 0, 0, 0, 0, 0, 0, 0, 0, 0, 0, 0, 0, 0, 0, 0, 0, 0, 0, 0, 0, 0, 0, 0, 0, 0, 0, 0 ],
          "Threshold_HV/key" : { "type" : 7, "num_values" : 96, "access_mode" : 7, "last_written" : 1731791277 },
          "Threshold_HV" : [ 0, 0, 0, 0, 0, 0, 0, 0, 0, 0, 0, 0, 0, 0, 0, 0, 0, 0, 0, 0, 0, 0, 0, 0, 0, 0, 0, 0, 0, 0, 0, 0, 0, 0, 0, 0, 0, 0, 0, 0, 0, 0, 0, 0, 0, 0, 0, 0, 0, 0, 0, 0, 0, 0, 0, 0, 0, 0, 0, 0, 0, 0, 0, 0, 0, 0, 0, 0, 0, 0, 0, 0, 0, 0, 0, 0, 0, 0, 0, 0, 0, 0, 0, 0, 0, 0, 0, 0, 0, 0, 0, 0, 0, 0, 0, 0 ],
          "Gain_CAL/key" : { "type" : 7, "num_values" : 96, "access_mode" : 7, "last_written" : 1731791277 },
          "Gain_CAL" : [ 0, 0, 0, 0, 0, 0, 0, 0, 0, 0, 0, 0, 0, 0, 0, 0, 0, 0, 0, 0, 0, 0, 0, 0, 0, 0, 0, 0, 0, 0, 0, 0, 0, 0, 0, 0, 0, 0, 0, 0, 0, 0, 0, 0, 0, 0, 0, 0, 0, 0, 0, 0, 0, 0, 0, 0, 0, 0, 0, 0, 0, 0, 0, 0, 0, 0, 0, 0, 0, 0, 0, 0, 0, 0, 0, 0, 0, 0, 0, 0, 0, 0, 0, 0, 0, 0, 0, 0, 0, 0, 0, 0, 0, 0, 0, 0 ],
          "Gain_HV/key" : { "type" : 7, "num_values" : 96, "access_mode" : 7, "last_written" : 1731791277 },
          "Gain_HV" : [ 0, 0, 0, 0, 0, 0, 0, 0, 0, 0, 0, 0, 0, 0, 0, 0, 0, 0, 0, 0, 0, 0, 0, 0, 0, 0, 0, 0, 0, 0, 0, 0, 0, 0, 0, 0, 0, 0, 0, 0, 0, 0, 0, 0, 0, 0, 0, 0, 0, 0, 0, 0, 0, 0, 0, 0, 0, 0, 0, 0, 0, 0, 0, 0, 0, 0, 0, 0, 0, 0, 0, 0, 0, 0, 0, 0, 0, 0, 0, 0, 0, 0, 0, 0, 0, 0, 0, 0, 0, 0, 0, 0, 0, 0, 0, 0 ],
          "ChannelMask/key" : { "type" : 6, "num_values" : 3, "access_mode" : 7, "last_written" : 1731791277 },
          "ChannelMask" : [ "0xffffffff", "0xffffffff", "0xffffffff" ],
          "Enabled/key" : { "type" : 7, "access_mode" : 7, "last_written" : 1731256909 },
          "Enabled" : 1,
          "Status/key" : { "type" : 7, "access_mode" : 7, "last_written" : 1731256407 },
          "Status" : 0
        },
        "Panel_05" : {
          "Name/key" : { "type" : 12, "item_size" : 32, "access_mode" : 7, "last_written" : 1731256536 },
          "Name" : "MN905",
          "Threshold_CAL/key" : { "type" : 7, "num_values" : 96, "access_mode" : 7, "last_written" : 1731791282 },
          "Threshold_CAL" : [ 0, 0, 0, 0, 0, 0, 0, 0, 0, 0, 0, 0, 0, 0, 0, 0, 0, 0, 0, 0, 0, 0, 0, 0, 0, 0, 0, 0, 0, 0, 0, 0, 0, 0, 0, 0, 0, 0, 0, 0, 0, 0, 0, 0, 0, 0, 0, 0, 0, 0, 0, 0, 0, 0, 0, 0, 0, 0, 0, 0, 0, 0, 0, 0, 0, 0, 0, 0, 0, 0, 0, 0, 0, 0, 0, 0, 0, 0, 0, 0, 0, 0, 0, 0, 0, 0, 0, 0, 0, 0, 0, 0, 0, 0, 0, 0 ],
          "Threshold_HV/key" : { "type" : 7, "num_values" : 96, "access_mode" : 7, "last_written" : 1731791282 },
          "Threshold_HV" : [ 0, 0, 0, 0, 0, 0, 0, 0, 0, 0, 0, 0, 0, 0, 0, 0, 0, 0, 0, 0, 0, 0, 0, 0, 0, 0, 0, 0, 0, 0, 0, 0, 0, 0, 0, 0, 0, 0, 0, 0, 0, 0, 0, 0, 0, 0, 0, 0, 0, 0, 0, 0, 0, 0, 0, 0, 0, 0, 0, 0, 0, 0, 0, 0, 0, 0, 0, 0, 0, 0, 0, 0, 0, 0, 0, 0, 0, 0, 0, 0, 0, 0, 0, 0, 0, 0, 0, 0, 0, 0, 0, 0, 0, 0, 0, 0 ],
          "Gain_CAL/key" : { "type" : 7, "num_values" : 96, "access_mode" : 7, "last_written" : 1731791282 },
          "Gain_CAL" : [ 0, 0, 0, 0, 0, 0, 0, 0, 0, 0, 0, 0, 0, 0, 0, 0, 0, 0, 0, 0, 0, 0, 0, 0, 0, 0, 0, 0, 0, 0, 0, 0, 0, 0, 0, 0, 0, 0, 0, 0, 0, 0, 0, 0, 0, 0, 0, 0, 0, 0, 0, 0, 0, 0, 0, 0, 0, 0, 0, 0, 0, 0, 0, 0, 0, 0, 0, 0, 0, 0, 0, 0, 0, 0, 0, 0, 0, 0, 0, 0, 0, 0, 0, 0, 0, 0, 0, 0, 0, 0, 0, 0, 0, 0, 0, 0 ],
          "Gain_HV/key" : { "type" : 7, "num_values" : 96, "access_mode" : 7, "last_written" : 1731791282 },
          "Gain_HV" : [ 0, 0, 0, 0, 0, 0, 0, 0, 0, 0, 0, 0, 0, 0, 0, 0, 0, 0, 0, 0, 0, 0, 0, 0, 0, 0, 0, 0, 0, 0, 0, 0, 0, 0, 0, 0, 0, 0, 0, 0, 0, 0, 0, 0, 0, 0, 0, 0, 0, 0, 0, 0, 0, 0, 0, 0, 0, 0, 0, 0, 0, 0, 0, 0, 0, 0, 0, 0, 0, 0, 0, 0, 0, 0, 0, 0, 0, 0, 0, 0, 0, 0, 0, 0, 0, 0, 0, 0, 0, 0, 0, 0, 0, 0, 0, 0 ],
          "ChannelMask/key" : { "type" : 6, "num_values" : 3, "access_mode" : 7, "last_written" : 1731791282 },
          "ChannelMask" : [ "0xffffffff", "0xffffffff", "0xffffffff" ],
          "Enabled/key" : { "type" : 7, "access_mode" : 7, "last_written" : 1731256914 },
          "Enabled" : 1,
          "Status/key" : { "type" : 7, "access_mode" : 7, "last_written" : 1731256413 },
          "Status" : 0
        },
        "Enabled/key" : { "type" : 7, "access_mode" : 7, "last_written" : 1731256935 },
        "Enabled" : 1,
        "Status/key" : { "type" : 7, "access_mode" : 7, "last_written" : 1731257087 },
        "Status" : 0,
        "DTC/key" : { "type" : 16, "link": "/Mu2e/RunConfigurations/roctower/DAQ/mu2edaq22/DTC0", "access_mode" : 7, "last_written" : 1731882337 },
        "DTC" : "/Mu2e/RunConfigurations/roctower/DAQ/mu2edaq22/DTC0"
      },
      "Plane_01" : {
        "Enabled/key" : { "type" : 7, "access_mode" : 7, "last_written" : 0 },
        "Enabled" : 0,
        "Status/key" : { "type" : 7, "access_mode" : 7, "last_written" : 1731257102 },
        "Status" : 0
      },
      "Enabled/key" : { "type" : 7, "access_mode" : 7, "last_written" : 1731256942 },
      "Enabled" : 1,
      "Status/key" : { "type" : 7, "access_mode" : 7, "last_written" : 1731257158 },
      "Status" : 0
    },
    "Station_01" : {
      "Plane_00" : {
        "Panel_00" : {
          "Name/key" : { "type" : 12, "item_size" : 32, "access_mode" : 7, "last_written" : 1731466200 },
          "Name" : "MN900",
          "Enabled/key" : { "type" : 7, "access_mode" : 7, "last_written" : 1731466200 },
          "Enabled" : 1,
          "ID/key" : { "type" : 12, "item_size" : 32, "access_mode" : 7, "last_written" : 1731466200 },
          "ID" : "",
          "FirstChannel/key" : { "type" : 7, "access_mode" : 7, "last_written" : 1731466200 },
          "FirstChannel" : 0,
          "Threshold_CAL/key" : { "type" : 7, "num_values" : 96, "access_mode" : 7, "last_written" : 1731466200 },
          "Threshold_CAL" : [ 0, 0, 0, 0, 0, 0, 0, 0, 0, 0, 0, 0, 0, 0, 0, 0, 0, 0, 0, 0, 0, 0, 0, 0, 0, 0, 0, 0, 0, 0, 0, 0, 0, 0, 0, 0, 0, 0, 0, 0, 0, 0, 0, 0, 0, 0, 0, 0, 0, 0, 0, 0, 0, 0, 0, 0, 0, 0, 0, 0, 0, 0, 0, 0, 0, 0, 0, 0, 0, 0, 0, 0, 0, 0, 0, 0, 0, 0, 0, 0, 0, 0, 0, 0, 0, 0, 0, 0, 0, 0, 0, 0, 0, 0, 0, 0 ],
          "Threshold_HV/key" : { "type" : 7, "num_values" : 96, "access_mode" : 7, "last_written" : 1731466200 },
          "Threshold_HV" : [ 0, 0, 0, 0, 0, 0, 0, 0, 0, 0, 0, 0, 0, 0, 0, 0, 0, 0, 0, 0, 0, 0, 0, 0, 0, 0, 0, 0, 0, 0, 0, 0, 0, 0, 0, 0, 0, 0, 0, 0, 0, 0, 0, 0, 0, 0, 0, 0, 0, 0, 0, 0, 0, 0, 0, 0, 0, 0, 0, 0, 0, 0, 0, 0, 0, 0, 0, 0, 0, 0, 0, 0, 0, 0, 0, 0, 0, 0, 0, 0, 0, 0, 0, 0, 0, 0, 0, 0, 0, 0, 0, 0, 0, 0, 0, 0 ],
          "Gain_CAL/key" : { "type" : 7, "num_values" : 96, "access_mode" : 7, "last_written" : 1731466200 },
          "Gain_CAL" : [ 0, 0, 0, 0, 0, 0, 0, 0, 0, 0, 0, 0, 0, 0, 0, 0, 0, 0, 0, 0, 0, 0, 0, 0, 0, 0, 0, 0, 0, 0, 0, 0, 0, 0, 0, 0, 0, 0, 0, 0, 0, 0, 0, 0, 0, 0, 0, 0, 0, 0, 0, 0, 0, 0, 0, 0, 0, 0, 0, 0, 0, 0, 0, 0, 0, 0, 0, 0, 0, 0, 0, 0, 0, 0, 0, 0, 0, 0, 0, 0, 0, 0, 0, 0, 0, 0, 0, 0, 0, 0, 0, 0, 0, 0, 0, 0 ],
          "Gain_HV/key" : { "type" : 7, "num_values" : 96, "access_mode" : 7, "last_written" : 1731466200 },
          "Gain_HV" : [ 0, 0, 0, 0, 0, 0, 0, 0, 0, 0, 0, 0, 0, 0, 0, 0, 0, 0, 0, 0, 0, 0, 0, 0, 0, 0, 0, 0, 0, 0, 0, 0, 0, 0, 0, 0, 0, 0, 0, 0, 0, 0, 0, 0, 0, 0, 0, 0, 0, 0, 0, 0, 0, 0, 0, 0, 0, 0, 0, 0, 0, 0, 0, 0, 0, 0, 0, 0, 0, 0, 0, 0, 0, 0, 0, 0, 0, 0, 0, 0, 0, 0, 0, 0, 0, 0, 0, 0, 0, 0, 0, 0, 0, 0, 0, 0 ],
          "ChannelMask/key" : { "type" : 6, "num_values" : 3, "access_mode" : 7, "last_written" : 1731466200 },
          "ChannelMask" : [ "0xffffffff", "0xffffffff", "0xffffffff" ],
          "# comment : Status:/key" : { "type" : 12, "item_size" : 59, "access_mode" : 7, "last_written" : 1731466200 },
          "# comment : Status:" : "0: undefined 1:being configured 2: configured -1: in error",
          "Status/key" : { "type" : 7, "access_mode" : 7, "last_written" : 1731466200 },
          "Status" : 0
        },
        "Panel_01" : {
          "Name/key" : { "type" : 12, "item_size" : 32, "access_mode" : 7, "last_written" : 1731466200 },
          "Name" : "MN901",
          "Enabled/key" : { "type" : 7, "access_mode" : 7, "last_written" : 1731466200 },
          "Enabled" : 1,
          "# comment : Status:/key" : { "type" : 12, "item_size" : 59, "access_mode" : 7, "last_written" : 1731466200 },
          "# comment : Status:" : "0: undefined 1:being configured 2: configured -1: in error",
          "Status/key" : { "type" : 7, "access_mode" : 7, "last_written" : 1731466200 },
          "Status" : 0
        },
        "Panel_02" : {
          "Name/key" : { "type" : 12, "item_size" : 32, "access_mode" : 7, "last_written" : 1731466200 },
          "Name" : "MN902",
          "Enabled/key" : { "type" : 7, "access_mode" : 7, "last_written" : 1731466200 },
          "Enabled" : 1,
          "# comment : Status:/key" : { "type" : 12, "item_size" : 59, "access_mode" : 7, "last_written" : 1731466200 },
          "# comment : Status:" : "0: undefined 1:being configured 2: configured -1: in error",
          "Status/key" : { "type" : 7, "access_mode" : 7, "last_written" : 1731466200 },
          "Status" : 0
        },
        "Enabled/key" : { "type" : 7, "access_mode" : 7, "last_written" : 1731466242 },
        "Enabled" : 0,
        "# comment : Status:/key" : { "type" : 12, "item_size" : 59, "access_mode" : 7, "last_written" : 1731466200 },
        "# comment : Status:" : "0: undefined 1:being configured 2: configured -1: in error",
        "Status/key" : { "type" : 7, "access_mode" : 7, "last_written" : 1731466200 },
        "Status" : 0,
        "Panel_05" : {
          "Name/key" : { "type" : 12, "item_size" : 32, "access_mode" : 7, "last_written" : 1731466200 },
          "Name" : "MN905",
          "Enabled/key" : { "type" : 7, "access_mode" : 7, "last_written" : 1731466200 },
          "Enabled" : 1,
          "# comment : Status:/key" : { "type" : 12, "item_size" : 59, "access_mode" : 7, "last_written" : 1731466200 },
          "# comment : Status:" : "0: undefined 1:being configured 2: configured -1: in error",
          "Status/key" : { "type" : 7, "access_mode" : 7, "last_written" : 1731466200 },
          "Status" : 0
        },
        "Panel_04" : {
          "Name/key" : { "type" : 12, "item_size" : 32, "access_mode" : 7, "last_written" : 1731466200 },
          "Name" : "MN904",
          "Enabled/key" : { "type" : 7, "access_mode" : 7, "last_written" : 1731466200 },
          "Enabled" : 1,
          "# comment : Status:/key" : { "type" : 12, "item_size" : 59, "access_mode" : 7, "last_written" : 1731466200 },
          "# comment : Status:" : "0: undefined 1:being configured 2: configured -1: in error",
          "Status/key" : { "type" : 7, "access_mode" : 7, "last_written" : 1731466200 },
          "Status" : 0
        },
        "Panel_03" : {
          "Name/key" : { "type" : 12, "item_size" : 32, "access_mode" : 7, "last_written" : 1731466200 },
          "Name" : "MN903",
          "Enabled/key" : { "type" : 7, "access_mode" : 7, "last_written" : 1731466200 },
          "Enabled" : 1,
          "# comment : Status:/key" : { "type" : 12, "item_size" : 59, "access_mode" : 7, "last_written" : 1731466200 },
          "# comment : Status:" : "0: undefined 1:being configured 2: configured -1: in error",
          "Status/key" : { "type" : 7, "access_mode" : 7, "last_written" : 1731466200 },
          "Status" : 0
        }
      },
      "Plane_01" : {
        "Enabled/key" : { "type" : 7, "access_mode" : 7, "last_written" : 1731466200 },
        "Enabled" : 0,
        "# comment : Status:/key" : { "type" : 12, "item_size" : 59, "access_mode" : 7, "last_written" : 1731466200 },
        "# comment : Status:" : "0: undefined 1:being configured 2: configured -1: in error",
        "Status/key" : { "type" : 7, "access_mode" : 7, "last_written" : 1731466200 },
        "Status" : 0
      },
      "Enabled/key" : { "type" : 7, "access_mode" : 7, "last_written" : 1731466221 },
      "Enabled" : 0,
      "Status/key" : { "type" : 7, "access_mode" : 7, "last_written" : 1731466200 },
      "Status" : 0
    },
    "Station_02" : {
      "Plane_00" : {
        "Panel_00" : {
          "Name/key" : { "type" : 12, "item_size" : 32, "access_mode" : 7, "last_written" : 1731466489 },
          "Name" : "MN900",
          "Enabled/key" : { "type" : 7, "access_mode" : 7, "last_written" : 1731466489 },
          "Enabled" : 1,
          "ID/key" : { "type" : 12, "item_size" : 32, "access_mode" : 7, "last_written" : 1731466489 },
          "ID" : "",
          "FirstChannel/key" : { "type" : 7, "access_mode" : 7, "last_written" : 1731466489 },
          "FirstChannel" : 0,
          "Threshold_CAL/key" : { "type" : 7, "num_values" : 96, "access_mode" : 7, "last_written" : 1731466489 },
          "Threshold_CAL" : [ 0, 0, 0, 0, 0, 0, 0, 0, 0, 0, 0, 0, 0, 0, 0, 0, 0, 0, 0, 0, 0, 0, 0, 0, 0, 0, 0, 0, 0, 0, 0, 0, 0, 0, 0, 0, 0, 0, 0, 0, 0, 0, 0, 0, 0, 0, 0, 0, 0, 0, 0, 0, 0, 0, 0, 0, 0, 0, 0, 0, 0, 0, 0, 0, 0, 0, 0, 0, 0, 0, 0, 0, 0, 0, 0, 0, 0, 0, 0, 0, 0, 0, 0, 0, 0, 0, 0, 0, 0, 0, 0, 0, 0, 0, 0, 0 ],
          "Threshold_HV/key" : { "type" : 7, "num_values" : 96, "access_mode" : 7, "last_written" : 1731466489 },
          "Threshold_HV" : [ 0, 0, 0, 0, 0, 0, 0, 0, 0, 0, 0, 0, 0, 0, 0, 0, 0, 0, 0, 0, 0, 0, 0, 0, 0, 0, 0, 0, 0, 0, 0, 0, 0, 0, 0, 0, 0, 0, 0, 0, 0, 0, 0, 0, 0, 0, 0, 0, 0, 0, 0, 0, 0, 0, 0, 0, 0, 0, 0, 0, 0, 0, 0, 0, 0, 0, 0, 0, 0, 0, 0, 0, 0, 0, 0, 0, 0, 0, 0, 0, 0, 0, 0, 0, 0, 0, 0, 0, 0, 0, 0, 0, 0, 0, 0, 0 ],
          "Gain_CAL/key" : { "type" : 7, "num_values" : 96, "access_mode" : 7, "last_written" : 1731466489 },
          "Gain_CAL" : [ 0, 0, 0, 0, 0, 0, 0, 0, 0, 0, 0, 0, 0, 0, 0, 0, 0, 0, 0, 0, 0, 0, 0, 0, 0, 0, 0, 0, 0, 0, 0, 0, 0, 0, 0, 0, 0, 0, 0, 0, 0, 0, 0, 0, 0, 0, 0, 0, 0, 0, 0, 0, 0, 0, 0, 0, 0, 0, 0, 0, 0, 0, 0, 0, 0, 0, 0, 0, 0, 0, 0, 0, 0, 0, 0, 0, 0, 0, 0, 0, 0, 0, 0, 0, 0, 0, 0, 0, 0, 0, 0, 0, 0, 0, 0, 0 ],
          "Gain_HV/key" : { "type" : 7, "num_values" : 96, "access_mode" : 7, "last_written" : 1731466489 },
          "Gain_HV" : [ 0, 0, 0, 0, 0, 0, 0, 0, 0, 0, 0, 0, 0, 0, 0, 0, 0, 0, 0, 0, 0, 0, 0, 0, 0, 0, 0, 0, 0, 0, 0, 0, 0, 0, 0, 0, 0, 0, 0, 0, 0, 0, 0, 0, 0, 0, 0, 0, 0, 0, 0, 0, 0, 0, 0, 0, 0, 0, 0, 0, 0, 0, 0, 0, 0, 0, 0, 0, 0, 0, 0, 0, 0, 0, 0, 0, 0, 0, 0, 0, 0, 0, 0, 0, 0, 0, 0, 0, 0, 0, 0, 0, 0, 0, 0, 0 ],
          "ChannelMask/key" : { "type" : 6, "num_values" : 3, "access_mode" : 7, "last_written" : 1731466489 },
          "ChannelMask" : [ "0xffffffff", "0xffffffff", "0xffffffff" ],
          "# comment : Status:/key" : { "type" : 12, "item_size" : 59, "access_mode" : 7, "last_written" : 1731466489 },
          "# comment : Status:" : "0: undefined 1:being configured 2: configured -1: in error",
          "Status/key" : { "type" : 7, "access_mode" : 7, "last_written" : 1731466489 },
          "Status" : 0
        },
        "Panel_01" : {
          "Name/key" : { "type" : 12, "item_size" : 32, "access_mode" : 7, "last_written" : 1731466489 },
          "Name" : "MN901",
          "Enabled/key" : { "type" : 7, "access_mode" : 7, "last_written" : 1731466489 },
          "Enabled" : 1,
          "# comment : Status:/key" : { "type" : 12, "item_size" : 59, "access_mode" : 7, "last_written" : 1731466489 },
          "# comment : Status:" : "0: undefined 1:being configured 2: configured -1: in error",
          "Status/key" : { "type" : 7, "access_mode" : 7, "last_written" : 1731466489 },
          "Status" : 0
        },
        "Panel_02" : {
          "Name/key" : { "type" : 12, "item_size" : 32, "access_mode" : 7, "last_written" : 1731466489 },
          "Name" : "MN902",
          "Enabled/key" : { "type" : 7, "access_mode" : 7, "last_written" : 1731466489 },
          "Enabled" : 1,
          "# comment : Status:/key" : { "type" : 12, "item_size" : 59, "access_mode" : 7, "last_written" : 1731466489 },
          "# comment : Status:" : "0: undefined 1:being configured 2: configured -1: in error",
          "Status/key" : { "type" : 7, "access_mode" : 7, "last_written" : 1731466489 },
          "Status" : 0
        },
        "Enabled/key" : { "type" : 7, "access_mode" : 7, "last_written" : 1731466489 },
        "Enabled" : 0,
        "# comment : Status:/key" : { "type" : 12, "item_size" : 59, "access_mode" : 7, "last_written" : 1731466489 },
        "# comment : Status:" : "0: undefined 1:being configured 2: configured -1: in error",
        "Status/key" : { "type" : 7, "access_mode" : 7, "last_written" : 1731466489 },
        "Status" : 0,
        "Panel_05" : {
          "Name/key" : { "type" : 12, "item_size" : 32, "access_mode" : 7, "last_written" : 1731466489 },
          "Name" : "MN905",
          "Enabled/key" : { "type" : 7, "access_mode" : 7, "last_written" : 1731466489 },
          "Enabled" : 1,
          "# comment : Status:/key" : { "type" : 12, "item_size" : 59, "access_mode" : 7, "last_written" : 1731466489 },
          "# comment : Status:" : "0: undefined 1:being configured 2: configured -1: in error",
          "Status/key" : { "type" : 7, "access_mode" : 7, "last_written" : 1731466489 },
          "Status" : 0
        },
        "Panel_04" : {
          "Name/key" : { "type" : 12, "item_size" : 32, "access_mode" : 7, "last_written" : 1731466489 },
          "Name" : "MN904",
          "Enabled/key" : { "type" : 7, "access_mode" : 7, "last_written" : 1731466489 },
          "Enabled" : 1,
          "# comment : Status:/key" : { "type" : 12, "item_size" : 59, "access_mode" : 7, "last_written" : 1731466489 },
          "# comment : Status:" : "0: undefined 1:being configured 2: configured -1: in error",
          "Status/key" : { "type" : 7, "access_mode" : 7, "last_written" : 1731466489 },
          "Status" : 0
        },
        "Panel_03" : {
          "Name/key" : { "type" : 12, "item_size" : 32, "access_mode" : 7, "last_written" : 1731466489 },
          "Name" : "MN903",
          "Enabled/key" : { "type" : 7, "access_mode" : 7, "last_written" : 1731466489 },
          "Enabled" : 1,
          "# comment : Status:/key" : { "type" : 12, "item_size" : 59, "access_mode" : 7, "last_written" : 1731466489 },
          "# comment : Status:" : "0: undefined 1:being configured 2: configured -1: in error",
          "Status/key" : { "type" : 7, "access_mode" : 7, "last_written" : 1731466489 },
          "Status" : 0
        }
      },
      "Plane_01" : {
        "Enabled/key" : { "type" : 7, "access_mode" : 7, "last_written" : 1731466489 },
        "Enabled" : 0,
        "# comment : Status:/key" : { "type" : 12, "item_size" : 59, "access_mode" : 7, "last_written" : 1731466489 },
        "# comment : Status:" : "0: undefined 1:being configured 2: configured -1: in error",
        "Status/key" : { "type" : 7, "access_mode" : 7, "last_written" : 1731466489 },
        "Status" : 0
      },
      "Enabled/key" : { "type" : 7, "access_mode" : 7, "last_written" : 1731466489 },
      "Enabled" : 0,
      "Status/key" : { "type" : 7, "access_mode" : 7, "last_written" : 1731466520 },
      "Status" : -1
    },
    "Station_03" : {
      "Plane_00" : {
        "Panel_00" : {
          "Name/key" : { "type" : 12, "item_size" : 32, "access_mode" : 7, "last_written" : 1731466491 },
          "Name" : "MN900",
          "Enabled/key" : { "type" : 7, "access_mode" : 7, "last_written" : 1731466491 },
          "Enabled" : 1,
          "ID/key" : { "type" : 12, "item_size" : 32, "access_mode" : 7, "last_written" : 1731466491 },
          "ID" : "",
          "FirstChannel/key" : { "type" : 7, "access_mode" : 7, "last_written" : 1731466491 },
          "FirstChannel" : 0,
          "Threshold_CAL/key" : { "type" : 7, "num_values" : 96, "access_mode" : 7, "last_written" : 1731466491 },
          "Threshold_CAL" : [ 0, 0, 0, 0, 0, 0, 0, 0, 0, 0, 0, 0, 0, 0, 0, 0, 0, 0, 0, 0, 0, 0, 0, 0, 0, 0, 0, 0, 0, 0, 0, 0, 0, 0, 0, 0, 0, 0, 0, 0, 0, 0, 0, 0, 0, 0, 0, 0, 0, 0, 0, 0, 0, 0, 0, 0, 0, 0, 0, 0, 0, 0, 0, 0, 0, 0, 0, 0, 0, 0, 0, 0, 0, 0, 0, 0, 0, 0, 0, 0, 0, 0, 0, 0, 0, 0, 0, 0, 0, 0, 0, 0, 0, 0, 0, 0 ],
          "Threshold_HV/key" : { "type" : 7, "num_values" : 96, "access_mode" : 7, "last_written" : 1731466491 },
          "Threshold_HV" : [ 0, 0, 0, 0, 0, 0, 0, 0, 0, 0, 0, 0, 0, 0, 0, 0, 0, 0, 0, 0, 0, 0, 0, 0, 0, 0, 0, 0, 0, 0, 0, 0, 0, 0, 0, 0, 0, 0, 0, 0, 0, 0, 0, 0, 0, 0, 0, 0, 0, 0, 0, 0, 0, 0, 0, 0, 0, 0, 0, 0, 0, 0, 0, 0, 0, 0, 0, 0, 0, 0, 0, 0, 0, 0, 0, 0, 0, 0, 0, 0, 0, 0, 0, 0, 0, 0, 0, 0, 0, 0, 0, 0, 0, 0, 0, 0 ],
          "Gain_CAL/key" : { "type" : 7, "num_values" : 96, "access_mode" : 7, "last_written" : 1731466491 },
          "Gain_CAL" : [ 0, 0, 0, 0, 0, 0, 0, 0, 0, 0, 0, 0, 0, 0, 0, 0, 0, 0, 0, 0, 0, 0, 0, 0, 0, 0, 0, 0, 0, 0, 0, 0, 0, 0, 0, 0, 0, 0, 0, 0, 0, 0, 0, 0, 0, 0, 0, 0, 0, 0, 0, 0, 0, 0, 0, 0, 0, 0, 0, 0, 0, 0, 0, 0, 0, 0, 0, 0, 0, 0, 0, 0, 0, 0, 0, 0, 0, 0, 0, 0, 0, 0, 0, 0, 0, 0, 0, 0, 0, 0, 0, 0, 0, 0, 0, 0 ],
          "Gain_HV/key" : { "type" : 7, "num_values" : 96, "access_mode" : 7, "last_written" : 1731466491 },
          "Gain_HV" : [ 0, 0, 0, 0, 0, 0, 0, 0, 0, 0, 0, 0, 0, 0, 0, 0, 0, 0, 0, 0, 0, 0, 0, 0, 0, 0, 0, 0, 0, 0, 0, 0, 0, 0, 0, 0, 0, 0, 0, 0, 0, 0, 0, 0, 0, 0, 0, 0, 0, 0, 0, 0, 0, 0, 0, 0, 0, 0, 0, 0, 0, 0, 0, 0, 0, 0, 0, 0, 0, 0, 0, 0, 0, 0, 0, 0, 0, 0, 0, 0, 0, 0, 0, 0, 0, 0, 0, 0, 0, 0, 0, 0, 0, 0, 0, 0 ],
          "ChannelMask/key" : { "type" : 6, "num_values" : 3, "access_mode" : 7, "last_written" : 1731466491 },
          "ChannelMask" : [ "0xffffffff", "0xffffffff", "0xffffffff" ],
          "# comment : Status:/key" : { "type" : 12, "item_size" : 59, "access_mode" : 7, "last_written" : 1731466491 },
          "# comment : Status:" : "0: undefined 1:being configured 2: configured -1: in error",
          "Status/key" : { "type" : 7, "access_mode" : 7, "last_written" : 1731466491 },
          "Status" : 0
        },
        "Panel_01" : {
          "Name/key" : { "type" : 12, "item_size" : 32, "access_mode" : 7, "last_written" : 1731466491 },
          "Name" : "MN901",
          "Enabled/key" : { "type" : 7, "access_mode" : 7, "last_written" : 1731466491 },
          "Enabled" : 1,
          "# comment : Status:/key" : { "type" : 12, "item_size" : 59, "access_mode" : 7, "last_written" : 1731466491 },
          "# comment : Status:" : "0: undefined 1:being configured 2: configured -1: in error",
          "Status/key" : { "type" : 7, "access_mode" : 7, "last_written" : 1731466491 },
          "Status" : 0
        },
        "Panel_02" : {
          "Name/key" : { "type" : 12, "item_size" : 32, "access_mode" : 7, "last_written" : 1731466491 },
          "Name" : "MN902",
          "Enabled/key" : { "type" : 7, "access_mode" : 7, "last_written" : 1731466491 },
          "Enabled" : 1,
          "# comment : Status:/key" : { "type" : 12, "item_size" : 59, "access_mode" : 7, "last_written" : 1731466491 },
          "# comment : Status:" : "0: undefined 1:being configured 2: configured -1: in error",
          "Status/key" : { "type" : 7, "access_mode" : 7, "last_written" : 1731466491 },
          "Status" : 0
        },
        "Enabled/key" : { "type" : 7, "access_mode" : 7, "last_written" : 1731466491 },
        "Enabled" : 0,
        "# comment : Status:/key" : { "type" : 12, "item_size" : 59, "access_mode" : 7, "last_written" : 1731466491 },
        "# comment : Status:" : "0: undefined 1:being configured 2: configured -1: in error",
        "Status/key" : { "type" : 7, "access_mode" : 7, "last_written" : 1731466491 },
        "Status" : 0,
        "Panel_05" : {
          "Name/key" : { "type" : 12, "item_size" : 32, "access_mode" : 7, "last_written" : 1731466491 },
          "Name" : "MN905",
          "Enabled/key" : { "type" : 7, "access_mode" : 7, "last_written" : 1731466491 },
          "Enabled" : 1,
          "# comment : Status:/key" : { "type" : 12, "item_size" : 59, "access_mode" : 7, "last_written" : 1731466491 },
          "# comment : Status:" : "0: undefined 1:being configured 2: configured -1: in error",
          "Status/key" : { "type" : 7, "access_mode" : 7, "last_written" : 1731466491 },
          "Status" : 0
        },
        "Panel_04" : {
          "Name/key" : { "type" : 12, "item_size" : 32, "access_mode" : 7, "last_written" : 1731466491 },
          "Name" : "MN904",
          "Enabled/key" : { "type" : 7, "access_mode" : 7, "last_written" : 1731466491 },
          "Enabled" : 1,
          "# comment : Status:/key" : { "type" : 12, "item_size" : 59, "access_mode" : 7, "last_written" : 1731466491 },
          "# comment : Status:" : "0: undefined 1:being configured 2: configured -1: in error",
          "Status/key" : { "type" : 7, "access_mode" : 7, "last_written" : 1731466491 },
          "Status" : 0
        },
        "Panel_03" : {
          "Name/key" : { "type" : 12, "item_size" : 32, "access_mode" : 7, "last_written" : 1731466491 },
          "Name" : "MN903",
          "Enabled/key" : { "type" : 7, "access_mode" : 7, "last_written" : 1731466491 },
          "Enabled" : 1,
          "# comment : Status:/key" : { "type" : 12, "item_size" : 59, "access_mode" : 7, "last_written" : 1731466491 },
          "# comment : Status:" : "0: undefined 1:being configured 2: configured -1: in error",
          "Status/key" : { "type" : 7, "access_mode" : 7, "last_written" : 1731466491 },
          "Status" : 0
        }
      },
      "Plane_01" : {
        "Enabled/key" : { "type" : 7, "access_mode" : 7, "last_written" : 1731466491 },
        "Enabled" : 0,
        "# comment : Status:/key" : { "type" : 12, "item_size" : 59, "access_mode" : 7, "last_written" : 1731466491 },
        "# comment : Status:" : "0: undefined 1:being configured 2: configured -1: in error",
        "Status/key" : { "type" : 7, "access_mode" : 7, "last_written" : 1731466491 },
        "Status" : 0
      },
      "Enabled/key" : { "type" : 7, "access_mode" : 7, "last_written" : 1731466491 },
      "Enabled" : 0,
      "Status/key" : { "type" : 7, "access_mode" : 7, "last_written" : 1731466525 },
      "Status" : -1
    },
    "Readout" : {
      "# -- comment #1/key" : { "type" : 12, "item_size" : 43, "access_mode" : 7, "last_written" : 1731214576 },
      "# -- comment #1" : "parameters of the control_ROC read command",
      "# -- comment # 2/key" : { "type" : 12, "item_size" : 41, "access_mode" : 7, "last_written" : 1731214576 },
      "# -- comment # 2" : "channel mask - individual for each panel",
      "AdcMode/key" : { "type" : 7, "access_mode" : 7, "last_written" : 1731214576 },
      "AdcMode" : 1,
      "TdcMode/key" : { "type" : 7, "access_mode" : 7, "last_written" : 1731214576 },
      "TdcMode" : 0,
      "NumLookback/key" : { "type" : 7, "access_mode" : 7, "last_written" : 1731214576 },
      "NumLookback" : 0,
      "NumSamples/key" : { "type" : 7, "access_mode" : 7, "last_written" : 1731214576 },
      "NumSamples" : 2,
      "EnablePulser/key" : { "type" : 7, "access_mode" : 7, "last_written" : 1731214576 },
      "EnablePulser" : 0,
      "NumTriggers/key" : { "type" : 7, "access_mode" : 7, "last_written" : 1731214576 },
      "NumTriggers" : 0,
      "MaxTotalDelay/key" : { "type" : 7, "access_mode" : 7, "last_written" : 1731214576 },
      "MaxTotalDelay" : 1,
      "MarkerClock/key" : { "type" : 7, "access_mode" : 7, "last_written" : 1731214576 },
      "MarkerClock" : 0
    },
    "Enabled/key" : { "type" : 7, "access_mode" : 7, "last_written" : 1731256993 },
    "Enabled" : 1,
    "Status/key" : { "type" : 7, "access_mode" : 7, "last_written" : 1731386509 },
    "Status" : 1,
    "MonitoringFrontend" : {
      "Name/key" : { "type" : 12, "item_size" : 32, "access_mode" : 7, "last_written" : 1733422816 },
      "Name" : "trkmon",
      "Host/key" : { "type" : 12, "item_size" : 32, "access_mode" : 7, "last_written" : 1733422807 },
      "Host" : "mu2edaq22-ctrl",
      "# --------------------- 1/key" : { "type" : 12, "item_size" : 32, "access_mode" : 7, "last_written" : 1733422807 },
      "# --------------------- 1" : "---------- configurable element",
      "Enabled/key" : { "type" : 7, "access_mode" : 7, "last_written" : 1733422807 },
      "Enabled" : 0,
      "Status/key" : { "type" : 7, "access_mode" : 7, "last_written" : 1733422807 },
      "Status" : 0
    }
  },
  "Trigger" : {
    "Table/key" : { "type" : 12, "item_size" : 64, "access_mode" : 7, "last_written" : 1732845185 },
    "Table" : "roctower_v01",
    "Enabled/key" : { "type" : 7, "access_mode" : 7, "last_written" : 1731214829 },
    "Enabled" : 0,
    "Status/key" : { "type" : 7, "access_mode" : 7, "last_written" : 0 },
    "Status" : 0,
    "MonitoringFrontend" : {
      "Name/key" : { "type" : 12, "item_size" : 32, "access_mode" : 7, "last_written" : 1733422841 },
      "Name" : "trigmon",
      "Host/key" : { "type" : 12, "item_size" : 32, "access_mode" : 7, "last_written" : 1733422831 },
      "Host" : "mu2edaq22-ctrl",
      "# --------------------- 1/key" : { "type" : 12, "item_size" : 32, "access_mode" : 7, "last_written" : 1733422831 },
      "# --------------------- 1" : "---------- configurable element",
      "Enabled/key" : { "type" : 7, "access_mode" : 7, "last_written" : 1733422831 },
      "Enabled" : 0,
      "Status/key" : { "type" : 7, "access_mode" : 7, "last_written" : 1733422831 },
      "Status" : 0
    }
  },
  "Status/key" : { "type" : 7, "access_mode" : 7, "last_written" : 1731736118 },
  "Status" : 0
}
